data/__init__.py
data/calib.pkl
data/df3d_result.pkl
df3d/__init__.py
df3d/cli.py
df3d/config.py
df3d/core.py
df3d/db.py
df3d/gui.py
df3d/logger.py
df3d/os_util.py
df3d/plot_util.py
df3d/procrustes.py
df3d/signal_util.py
df3d/skeleton_fly.py
df3d/video.py
nely_df3d-1.0.1.dist-info/licenses/AUTHORS
nely_df3d-1.0.1.dist-info/licenses/LICENSE
tests/__init__.py
tests/test_df3d.py
nely_df3d-1.0.1.dist-info/METADATA
nely_df3d-1.0.1.dist-info/WHEEL
nely_df3d-1.0.1.dist-info/entry_points.txt
nely_df3d-1.0.1.dist-info/top_level.txt
nely_df3d-1.0.1.dist-info/RECORD
