Metadata-Version: 2.4
Name: nely-df3d
Version: 1.0.1
Summary: GUI and 3D pose estimation pipeline for tethered Drosophila.
Home-page: https://github.com/NeLy-EPFL/DeepFly3D
Author: Semih Gunel
Author-email: gunelsemih@gmail.com
Requires-Python: >=3.8
License-File: LICENSE
License-File: AUTHORS
Requires-Dist: colorama
Requires-Dist: matplotlib
Requires-Dist: numpy
Requires-Dist: opencv-python-headless>=4.8.1.78
Requires-Dist: PyQt5
Requires-Dist: scikit-learn
Requires-Dist: tqdm
Requires-Dist: nely-pyba>=0.13
Requires-Dist: nely-df2d>=0.14
Dynamic: author
Dynamic: author-email
Dynamic: description
Dynamic: description-content-type
Dynamic: home-page
Dynamic: license-file
Dynamic: requires-dist
Dynamic: requires-python
Dynamic: summary
